triflow/__init__.py
triflow/core/__init__.py
triflow/core/compilers.py
triflow/core/fields.py
triflow/core/model.py
triflow/core/routines.py
triflow/core/schemes.py
triflow/core/simulation.py
triflow/plugins/__init__.py
triflow/plugins/container.py
triflow/plugins/displays.py
triflow-0.5.2.dist-info/LICENSE
triflow-0.5.2.dist-info/WHEEL
triflow-0.5.2.dist-info/METADATA
triflow-0.5.2.dist-info/RECORD
